motioncapture.cpython-313-darwin.so
motioncapture-1.0a4.dist-info/LICENSE
motioncapture-1.0a4.dist-info/METADATA
motioncapture-1.0a4.dist-info/WHEEL
motioncapture-1.0a4.dist-info/top_level.txt
motioncapture-1.0a4.dist-info/RECORD
