Metadata-Version: 2.1
Name: motioncapture
Version: 1.0a4
Summary: Interface for common motion capture systems
Home-page: UNKNOWN
License: UNKNOWN
Platform: UNKNOWN
License-File: LICENSE
